hooks_vb/__init__.py
hooks_vb/add_version_tag.py
hooks_vb/build_utils.py
hooks_vb/check_commit_msg.py
hooks_vb/git_utils.py
hooks_vb/publish.py
hooks_vb-0.0.6.dist-info/LICENSE
hooks_vb-0.0.6.dist-info/METADATA
hooks_vb-0.0.6.dist-info/WHEEL
hooks_vb-0.0.6.dist-info/entry_points.txt
hooks_vb-0.0.6.dist-info/top_level.txt
hooks_vb-0.0.6.dist-info/RECORD
