Metadata-Version: 2.1
Name: hooks-vb
Version: 0.0.6
Summary: Pre-commit app hooks.
Home-page: https://github.com/violet-black/hooks-vb
Author: Violet Black
Author-email: violetblackdev@gmail.com
License: Apache-2.0
Keywords: pre-commit,git,hooks
Platform: UNKNOWN
Classifier: Development Status :: 3 - Alpha
Classifier: License :: OSI Approved :: Apache Software License
Classifier: Programming Language :: Python :: 3
Classifier: Programming Language :: Python :: 3 :: Only
Classifier: Programming Language :: Python :: 3.6
Classifier: Programming Language :: Python :: 3.7
Classifier: Programming Language :: Python :: 3.8
Classifier: Programming Language :: Python :: 3.9
Classifier: Programming Language :: Python :: 3.10
Classifier: Programming Language :: Python :: Implementation :: CPython
Requires-Python: >=3.6
License-File: LICENSE
Requires-Dist: build (>=0.7.0)
Requires-Dist: pep440 (>=0.1.0)
Requires-Dist: pip (>=21.3.1)
Requires-Dist: restructuredtext-lint (>=1.3.2)
Requires-Dist: twine (>=3.4.2)
Provides-Extra: dev
Requires-Dist: codecov (>=2.1.12) ; extra == 'dev'
Requires-Dist: coverage (>=6.0.2) ; extra == 'dev'
Requires-Dist: pre-commit (>=2.15) ; extra == 'dev'
Requires-Dist: pytest (>=6.2) ; extra == 'dev'
Requires-Dist: tox (>=3.24) ; extra == 'dev'
Requires-Dist: tox-pyenv (>=1.1.0) ; extra == 'dev'
Provides-Extra: docs
Requires-Dist: docutils (==0.17.1) ; extra == 'docs'
Requires-Dist: sphinx ; extra == 'docs'
